us_libraries/__init__.py
us_libraries/client/__init__.py
us_libraries/client/base_client.py
us_libraries/client/exceptions.py
us_libraries/constants/__init__.py
us_libraries/constants/http_code.py
us_libraries/flask_service_exceptions/__init__.py
us_libraries/flask_service_exceptions/exceptions.py
us_libraries/graphite/__init__.py
us_libraries/graphite/constants.py
us_libraries/graphite/graphite_client.py
us_libraries/graphite/statsclients.py
us_libraries/graphite/statsd.py
us_libraries/service/__init__.py
us_libraries/service/service_config.py
us_libraries/utils/__init__.py
us_libraries/utils/formatters.py
us_libraries-0.0.14.dist-info/METADATA
us_libraries-0.0.14.dist-info/WHEEL
us_libraries-0.0.14.dist-info/top_level.txt
us_libraries-0.0.14.dist-info/RECORD
