Metadata-Version: 2.1
Name: us-libraries
Version: 0.0.14
Summary: Libraries for us services
Home-page: https://github.com/ukuspeed
Author: Ukuspeed
Author-email: info@ukuspeed.gmail.com
License: UNKNOWN
Platform: UNKNOWN
Classifier: Programming Language :: Python :: 3
Classifier: License :: OSI Approved :: MIT License
Classifier: Operating System :: OS Independent
Requires-Python: >=3.6
Requires-Dist: getconf
Requires-Dist: srvlookup
Requires-Dist: dnspython
Requires-Dist: requests
Requires-Dist: graphyte
Requires-Dist: dataclasses
Requires-Dist: typing-extensions
Requires-Dist: pyramid
Requires-Dist: pyramid-swagger
Provides-Extra: dev
Requires-Dist: pre-commit ; extra == 'dev'
